llama_index/llms/litellm/__init__.py
llama_index/llms/litellm/base.py
llama_index/llms/litellm/utils.py
llama_index_llms_litellm-0.6.3.dist-info/METADATA
llama_index_llms_litellm-0.6.3.dist-info/WHEEL
llama_index_llms_litellm-0.6.3.dist-info/licenses/LICENSE
llama_index_llms_litellm-0.6.3.dist-info/RECORD
